odoo/addons/product_supplierinfo_security/README.rst
odoo/addons/product_supplierinfo_security/__init__.py
odoo/addons/product_supplierinfo_security/__manifest__.py
odoo/addons/product_supplierinfo_security/i18n/it.po
odoo/addons/product_supplierinfo_security/i18n/product_supplierinfo_security.pot
odoo/addons/product_supplierinfo_security/readme/CONTEXT.md
odoo/addons/product_supplierinfo_security/readme/CONTRIBUTORS.md
odoo/addons/product_supplierinfo_security/readme/DESCRIPTION.md
odoo/addons/product_supplierinfo_security/readme/ROADMAP.md
odoo/addons/product_supplierinfo_security/readme/USAGE.md
odoo/addons/product_supplierinfo_security/static/description/icon.png
odoo/addons/product_supplierinfo_security/static/description/index.html
odoo/addons/product_supplierinfo_security/tests/__init__.py
odoo/addons/product_supplierinfo_security/tests/test_product_supplierinfo_security.py
odoo/addons/product_supplierinfo_security/views/product_views.xml
odoo_addon_product_supplierinfo_security-16.0.1.0.0.3.dist-info/METADATA
odoo_addon_product_supplierinfo_security-16.0.1.0.0.3.dist-info/WHEEL
odoo_addon_product_supplierinfo_security-16.0.1.0.0.3.dist-info/top_level.txt
odoo_addon_product_supplierinfo_security-16.0.1.0.0.3.dist-info/RECORD
