Metadata-Version: 2.1
Name: odoo-addon-product_supplierinfo_security
Version: 16.0.1.0.0.3
Summary: Restricts access to supplier information on products.
Home-page: https://github.com/OCA/purchase-workflow
Author: Moduon, Odoo Community Association (OCA)
Author-email: support@odoo-community.org
License: LGPL-3
Classifier: Programming Language :: Python
Classifier: Framework :: Odoo
Classifier: Framework :: Odoo :: 16.0
Classifier: License :: OSI Approved :: GNU Lesser General Public License v3 (LGPLv3)
Requires-Python: >=3.10
Requires-Dist: odoo<16.1dev,>=16.0a
